smartsettings/__init__.py
smartsettings/smartsettings.py
smartsettings-0.2.0.dist-info/LICENSE
smartsettings-0.2.0.dist-info/METADATA
smartsettings-0.2.0.dist-info/WHEEL
smartsettings-0.2.0.dist-info/top_level.txt
smartsettings-0.2.0.dist-info/RECORD
