Metadata-Version: 2.1
Name: smartsettings
Version: 0.2.0
Summary: Smart Settings
Author-email: Quan Lin <jacklinquan@gmail.com>
License: MIT License
Project-URL: Homepage, https://github.com/jacklinquan/smartsettings
Keywords: json,settings
Classifier: License :: OSI Approved :: MIT License
Classifier: Programming Language :: Python
Classifier: Programming Language :: Python :: 3
Requires-Python: >=3.7
License-File: LICENSE
Requires-Dist: jsonpickle
Requires-Dist: cryptomsg
Provides-Extra: dev
Requires-Dist: black ; extra == 'dev'
Requires-Dist: pytest ; extra == 'dev'
